corec/__init__.py
corec/evaluation/__init__.py
corec/evaluation/constants.py
corec/evaluation/evaluator.py
corec/evaluation/metric_generator.py
corec/evaluation/qrels_generator.py
corec/evaluation/run_generator.py
corec/evaluation/utils.py
corec/postfilters/__init__.py
corec/postfilters/postfilter.py
corec/recommenders/__init__.py
corec/recommenders/base_rec.py
corec/recommenders/elliot_rec/__init__.py
corec/recommenders/elliot_rec/constants.py
corec/recommenders/elliot_rec/elliot_rec.py
corec/recommenders/heuristic_recs/__init__.py
corec/recommenders/heuristic_recs/context_pop.py
corec/recommenders/heuristic_recs/context_random.py
corec/recommenders/heuristic_recs/context_satisfaction.py
corec/recommenders/heuristic_recs/heuristic_rec.py
corec/recommenders/recbole_rec/__init__.py
corec/recommenders/recbole_rec/recbole_rec.py
corec/utils/__init__.py
corec/utils/utils.py
corec-1.1.5.dist-info/LICENSE
corec-1.1.5.dist-info/METADATA
corec-1.1.5.dist-info/WHEEL
corec-1.1.5.dist-info/top_level.txt
corec-1.1.5.dist-info/RECORD
