Metadata-Version: 2.1
Name: corec
Version: 1.1.5
Summary: A Context-Aware Recommendation Framework for Python
Author-email: Jaime Gimillo <jaimegimillo@gmail.com>
License: LICENSE
Keywords: recommender,context-aware,evaluation,framework
Classifier: Programming Language :: Python :: 3.8
Classifier: License :: OSI Approved :: MIT License
Classifier: Operating System :: OS Independent
Requires-Python: <3.9,>=3.8
License-File: LICENSE
Requires-Dist: pydantic==2.10.6
Requires-Dist: protobuf==3.20.*
Provides-Extra: evaluator
Requires-Dist: ranx==0.3.20; extra == "evaluator"
Provides-Extra: recommender
